README.md
hre.py
setup.py
hre.egg-info/PKG-INFO
hre.egg-info/SOURCES.txt
hre.egg-info/dependency_links.txt
hre.egg-info/top_level.txt